prescient/__init__.py
prescient/__main__.py
prescient/utils.py
prescient/commands/__init__.py
prescient/commands/perturbation_analysis.py
prescient/commands/process_data.py
prescient/commands/simulate_trajectories.py
prescient/commands/train_model.py
prescient/perturb/__init__.py
prescient/perturb/pert.py
prescient/simulate/__init__.py
prescient/simulate/sim.py
prescient/train/__init__.py
prescient/train/model.py
prescient/train/run.py
prescient/train/util.py
prescient-0.1.0.dist-info/METADATA
prescient-0.1.0.dist-info/WHEEL
prescient-0.1.0.dist-info/entry_points.txt
prescient-0.1.0.dist-info/top_level.txt
prescient-0.1.0.dist-info/RECORD
