Metadata-Version: 2.1
Name: prescient
Version: 0.1.0
Summary: Method for simulating single cells using longitudinal scRNA-seq.
Home-page: https://github.com/gifford-lab/prescient
Author: Sachit Saksena; Grace Hui-Ting Yeo
Author-email: sachit@mit.edu
License: MIT License
Platform: UNKNOWN
Classifier: Intended Audience :: Science/Research
Classifier: License :: OSI Approved :: MIT License
Classifier: Operating System :: OS Independent
Classifier: Programming Language :: Python :: 3
Requires-Python: >=3.4
Requires-Dist: scanpy (>=1.7)
Requires-Dist: pyreadr (>=0.0)
Requires-Dist: matplotlib (>=3.3)
Requires-Dist: annoy (>=1.17.0)
Requires-Dist: numpy (>=1.14)
Requires-Dist: pandas (>=0.25)
Requires-Dist: scikit-learn (>=0.21)
Requires-Dist: scipy (>=1.3)
Requires-Dist: setuptools (>=41.6)
Requires-Dist: torch (>=1.5)
Requires-Dist: torchvision (>=0.7)
Requires-Dist: geomloss (==0.2.3)
Requires-Dist: pykeops (>=1.3)
